frontend_assets/__init__.py
frontend_assets/static/cdn.json
frontend_assets/static/css/all.css
frontend_assets/static/css/all.min.css
frontend_assets/static/css/brands.css
frontend_assets/static/css/brands.min.css
frontend_assets/static/css/font-awesome-4.css
frontend_assets/static/css/font-awesome-4.css.map
frontend_assets/static/css/font-awesome-4.min.css
frontend_assets/static/css/fontawesome.css
frontend_assets/static/css/fontawesome.min.css
frontend_assets/static/css/leaflet.css
frontend_assets/static/css/regular.css
frontend_assets/static/css/regular.min.css
frontend_assets/static/css/solid.css
frontend_assets/static/css/solid.min.css
frontend_assets/static/css/svg-with-js.css
frontend_assets/static/css/svg-with-js.min.css
frontend_assets/static/css/v4-shims.css
frontend_assets/static/css/v4-shims.min.css
frontend_assets/static/css/images/layers-2x.png
frontend_assets/static/css/images/layers.png
frontend_assets/static/css/images/marker-icon-2x.png
frontend_assets/static/css/images/marker-icon.png
frontend_assets/static/css/images/marker-shadow.png
frontend_assets/static/fonts/FontAwesome.otf
frontend_assets/static/fonts/fa-solid-900.woff
frontend_assets/static/fonts/fontawesome-4-webfont.eot
frontend_assets/static/fonts/fontawesome-4-webfont.svg
frontend_assets/static/fonts/fontawesome-4-webfont.ttf
frontend_assets/static/fonts/fontawesome-4-webfont.woff
frontend_assets/static/fonts/fontawesome-4-webfont.woff2
frontend_assets/static/fonts/icons/entypo.eot
frontend_assets/static/fonts/icons/entypo.ttf
frontend_assets/static/fonts/icons/entypo.woff
frontend_assets/static/js/all.js
frontend_assets/static/js/all.min.js
frontend_assets/static/js/brands.js
frontend_assets/static/js/brands.min.js
frontend_assets/static/js/fontawesome.js
frontend_assets/static/js/fontawesome.min.js
frontend_assets/static/js/ieshiv.js
frontend_assets/static/js/jquery-3.3.1.js
frontend_assets/static/js/jquery-3.3.1.min.js
frontend_assets/static/js/jquery-3.3.1.slim.js
frontend_assets-0.8.1.dist-info/LICENSE
frontend_assets-0.8.1.dist-info/METADATA
frontend_assets-0.8.1.dist-info/WHEEL
frontend_assets-0.8.1.dist-info/top_level.txt
frontend_assets-0.8.1.dist-info/RECORD
