Metadata-Version: 2.1
Name: frontend-assets
Version: 0.8.1
Summary: A collection of front-end assets I use for several sites
Home-page: https://github.com/avryhof/frontend_assets
Author: Amos Vryhof
Author-email: amos@vryhofresearch.com
License: MIT
Platform: UNKNOWN
Classifier: Development Status :: 5 - Production/Stable
Classifier: Intended Audience :: Developers
Classifier: License :: OSI Approved :: MIT License
Classifier: Programming Language :: Python :: 3
License-File: LICENSE
Requires-Dist: django
Requires-Dist: django-bootstrap4
Requires-Dist: future
Requires-Dist: requests
Requires-Dist: subresource-integrity
